Metadata-Version: 2.1
Name: RobotFrameworkElasticSearchLibrary
Version: 0.0.6
Summary: Robot Framework ElasticSearch library.
Home-page: https://github.com/gianpaolocaprara/robotframework-elasticsearch
Author: Gianpaolo Caprara
Author-email: gianpaolo.caprara@gmail.com
License: MIT
Keywords: ROBOTFRAMEWORK,ELASTICSEARCH
Platform: UNKNOWN
Classifier: License :: OSI Approved :: MIT License
Classifier: Programming Language :: Python :: 3.6
Classifier: Programming Language :: Python :: 3.7
Classifier: Programming Language :: Python :: 3.8
